litedocai/__init__.py
litedocai/anl_result.py
litedocai-0.1.2.dist-info/METADATA
litedocai-0.1.2.dist-info/WHEEL
litedocai-0.1.2.dist-info/RECORD
