Metadata-Version: 2.1
Name: litedocai
Version: 0.1.2
Summary: Call all Document AI APIs using a common format. Use Azure, Google, Amazon or own system.
License: MIT
Author: Enrique
Author-email: ebotiabarbera@gmail.com
Requires-Python: >=3.10,<4.0
Classifier: License :: OSI Approved :: MIT License
Classifier: Programming Language :: Python :: 3
Classifier: Programming Language :: Python :: 3.10
Classifier: Programming Language :: Python :: 3.11
Classifier: Programming Language :: Python :: 3.12
Requires-Dist: azure-ai-documentintelligence (>=1.0.0b3,<2.0.0)
